<?xml version="1.0" encoding="UTF-8"?>
<?xml-model href="http://www.loc.gov/standards/vracore/vra-strict.xsd"?>

<vra xmlns="http://www.vraweb.org/vracore4.htm">

<work id="wfc.img.pht00109">
<agentSet>
<display></display>
<agent>
<name></name>
<dates></dates>
<role></role>
</agent>
</agentSet> 
<dateSet>
<display>1891</display>
<date><earliestDate>1891</earliestDate><latestDate>1891</latestDate></date>
</dateSet>
<descriptionSet>
<description>In this stereocard, Lakota performers with Buffalo Bill's Wild West pose in front of a tepee during the show's appearance in Brussels in 1891.</description>
</descriptionSet>
<inscriptionSet>
<inscription>
<text></text>
</inscription>
</inscriptionSet>
<locationSet>
<location>
<name></name>
</location>
</locationSet>
<relationSet>
<relation>Friesen, Steve. Lakota Performers in Europe: Their Culture and the Artifacts They Left Behind. University of Oklahoma Press, 2017.</relation>
<relation>http://www.codystudies.org/friesen/</relation>
</relationSet>
<rightsSet>
<rights>
<rightsHolder>Buffalo Bill Museum and Grave</rightsHolder>
<text></text>
</rights>
</rightsSet>
<sourceSet>
<display></display>
<source>
<name type="electronic"></name>
</source>
</sourceSet>
<subjectSet>
<display>Lakota Performers</display>
<subject>
<term>American Indians</term>
<term></term>
<term></term>
<term></term>
<term></term>
<term></term>
<term></term>
</subject>
</subjectSet>
<techniqueSet>
<technique></technique>
</techniqueSet>   
<titleSet>
<title>Lakota Performers in Brussels</title>
</titleSet>
<worktypeSet>
<worktype>photograph</worktype>
</worktypeSet>
<image>
<agentSet>
<agent>
<name type="personal"></name>
<role></role>
</agent>
</agentSet>
<dateSet>
<date></date>
</dateSet>
<relationSet>
<relation/>
</relationSet>
<rightsSet>
<rights>
<rightsHolder>Buffalo Bill Museum and Grave</rightsHolder>
<text></text>
</rights> 
</rightsSet>
<worktypeSet>
<worktype>digital image</worktype>
</worktypeSet>
</image>
</work> 

</vra>